LICENSE.txt
MANIFEST.in
Makefile
README.rst
setup.py
docs/Makefile
docs/source/conf.py
docs/source/index.rst
docs/source/setup.rst
docs/source/modules/modules.rst
docs/source/modules/nasapi.rst
docs/source/modules/nasapi.tests.rst
nasapi/__init__.py
nasapi/api.py
nasapi/tests/__init__.py
nasapi/tests/test_api.py
python_nasapi.egg-info/PKG-INFO
python_nasapi.egg-info/SOURCES.txt
python_nasapi.egg-info/dependency_links.txt
python_nasapi.egg-info/requires.txt
python_nasapi.egg-info/top_level.txt