Metadata-Version: 1.1
Name: python-nasapi
Version: 0.1
Summary: Python-nasapi is a client library for the NASA api endpoints.
Home-page: https://github.com/lockwooddev/python-nasapi
Author: Carlo Smouter
Author-email: lockwooddev@gmail.com
License: MIT
Keywords: nasa,api
Platform: UNKNOWN
Classifier: Development Status :: 4 - Beta
Classifier: Intended Audience :: Developers
Classifier: License :: OSI Approved :: MIT License
Classifier: Operating System :: OS Independent
Classifier: Programming Language :: Python :: 3.4
Classifier: Topic :: Internet :: WWW/HTTP
